threedigrid/__init__.py
threedigrid/geo_utils.py
threedigrid/numpy_utils.py
threedigrid/admin/__init__.py
threedigrid/admin/constants.py
threedigrid/admin/exporter_constants.py
threedigrid/admin/gridadmin.py
threedigrid/admin/gridresultadmin.py
threedigrid/admin/h5py_datasource.py
threedigrid/admin/h5py_swmr.py
threedigrid/admin/idmapper.py
threedigrid/admin/prepare.py
threedigrid/admin/prepare_utils.py
threedigrid/admin/rpc_datasource.py
threedigrid/admin/serializers.py
threedigrid/admin/utils.py
threedigrid/admin/breaches/__init__.py
threedigrid/admin/breaches/exporters.py
threedigrid/admin/breaches/models.py
threedigrid/admin/breaches/prepare.py
threedigrid/admin/breaches/timeseries_mixin.py
threedigrid/admin/crosssections/__init__.py
threedigrid/admin/crosssections/models.py
threedigrid/admin/exporters/__init__.py
threedigrid/admin/exporters/geopackage/__init__.py
threedigrid/admin/exporters/geopackage/default.py
threedigrid/admin/exporters/geopackage/exporter.py
threedigrid/admin/fragments/__init__.py
threedigrid/admin/fragments/exporters.py
threedigrid/admin/fragments/models.py
threedigrid/admin/levees/__init__.py
threedigrid/admin/levees/exporters.py
threedigrid/admin/levees/models.py
threedigrid/admin/levees/prepare.py
threedigrid/admin/lines/__init__.py
threedigrid/admin/lines/exporters.py
threedigrid/admin/lines/models.py
threedigrid/admin/lines/prepare.py
threedigrid/admin/lines/subsets.py
threedigrid/admin/lines/timeseries_mixin.py
threedigrid/admin/nodes/__init__.py
threedigrid/admin/nodes/exporters.py
threedigrid/admin/nodes/models.py
threedigrid/admin/nodes/prepare.py
threedigrid/admin/nodes/subsets.py
threedigrid/admin/nodes/timeseries_mixin.py
threedigrid/admin/pumps/__init__.py
threedigrid/admin/pumps/models.py
threedigrid/admin/pumps/prepare.py
threedigrid/admin/pumps/timeseries_mixin.py
threedigrid/admin/structure_controls/__init__.py
threedigrid/admin/structure_controls/exporters.py
threedigrid/admin/structure_controls/models.py
threedigrid-2.3.6.dist-info/licenses/AUTHORS.rst
threedigrid-2.3.6.dist-info/licenses/LICENSE
threedigrid-2.3.6.dist-info/METADATA
threedigrid-2.3.6.dist-info/WHEEL
threedigrid-2.3.6.dist-info/entry_points.txt
threedigrid-2.3.6.dist-info/top_level.txt
threedigrid-2.3.6.dist-info/RECORD
