Metadata-Version: 2.4
Name: threedigrid
Version: 2.3.6
Summary: Python package for the threedigrid administration
Home-page: https://github.com/nens/threedigrid
Author: Lars Claussen
Author-email: info@nelen-schuurmans.nl
License: BSD license
Keywords: threedigrid
Classifier: Development Status :: 4 - Beta
Classifier: Intended Audience :: Developers
Classifier: License :: OSI Approved :: BSD License
Classifier: Natural Language :: English
Classifier: Programming Language :: Python :: 3
Classifier: Topic :: Scientific/Engineering
Requires-Python: >=3.8
License-File: LICENSE
License-File: AUTHORS.rst
Requires-Dist: numpy>=1.15
Requires-Dist: h5py>=2.9
Requires-Dist: six
Provides-Extra: geo
Requires-Dist: Click>=6.0; extra == "geo"
Requires-Dist: mercantile>=1.0.4; extra == "geo"
Requires-Dist: pyproj>=2.2; extra == "geo"
Requires-Dist: Shapely>=1.6; extra == "geo"
Requires-Dist: geojson>=2.4; extra == "geo"
Provides-Extra: results
Requires-Dist: cftime>=1.0.1; extra == "results"
Provides-Extra: rpc
Requires-Dist: asyncio-rpc>=0.1.10; extra == "rpc"
Provides-Extra: docs
Requires-Dist: sphinx~=7.2.6; extra == "docs"
Requires-Dist: sphinx_rtd_theme>=2.0.0; extra == "docs"
Dynamic: author
Dynamic: author-email
Dynamic: classifier
Dynamic: description
Dynamic: home-page
Dynamic: keywords
Dynamic: license
Dynamic: license-file
Dynamic: provides-extra
Dynamic: requires-dist
Dynamic: requires-python
Dynamic: summary
